LICENSE
README.md
setup.py
CVE_2000_0114.egg-info/PKG-INFO
CVE_2000_0114.egg-info/SOURCES.txt
CVE_2000_0114.egg-info/dependency_links.txt
CVE_2000_0114.egg-info/entry_points.txt
CVE_2000_0114.egg-info/requires.txt
CVE_2000_0114.egg-info/top_level.txt
cve20000114/__init__.py
cve20000114/main.py
cve20000114/includes/__init__.py
cve20000114/includes/bot.py
cve20000114/includes/filereader.py
cve20000114/includes/scan.py
cve20000114/includes/writefile.py
cve20000114/utils/__init__.py
cve20000114/utils/configure.py
cve20000114/utils/const.py
cve20000114/utils/helpers.py
cve20000114/utils/status.py